pycpfcnpj/__init__.py
pycpfcnpj/calculation.py
pycpfcnpj/cnpj.py
pycpfcnpj/compatible.py
pycpfcnpj/cpf.py
pycpfcnpj/cpfcnpj.py
pycpfcnpj/gen.py
pycpfcnpj/mask.py
tests/__init__.py
tests/calculation_tests.py
tests/cnpj_tests.py
tests/cpf_tests.py
tests/cpfcnpj_tests.py
tests/format_tests.py
tests/gen_test.py
cpf_cnpj_validate-1.4.dist-info/LICENSE
cpf_cnpj_validate-1.4.dist-info/METADATA
cpf_cnpj_validate-1.4.dist-info/WHEEL
cpf_cnpj_validate-1.4.dist-info/top_level.txt
cpf_cnpj_validate-1.4.dist-info/RECORD
