Metadata-Version: 2.1
Name: cpf_cnpj_validate
Version: 1.4
Summary: Python module for brazilian register numbers for persons (CPF) and companies (CNPJ) and mask generator to string or int CPF/CNPJ.
Home-page: https://github.com/andrersp/pycpfcnpj
Author: André França
Author-email: rsp.assistencia@gmail.com
License: MIT
Keywords: cpf cnpj validation generation mask
Platform: UNKNOWN
Classifier: Development Status :: 5 - Production/Stable
Classifier: License :: OSI Approved :: MIT License
Classifier: Programming Language :: Python :: 3
Classifier: Programming Language :: Python :: 3.2
Classifier: Programming Language :: Python :: 3.3
Classifier: Programming Language :: Python :: 3.6
Classifier: Programming Language :: Python :: 3.7
Classifier: Programming Language :: Python :: 3.8
Classifier: Programming Language :: Python :: 3.9
Classifier: Programming Language :: Python :: 3.10
Classifier: Topic :: Software Development :: Libraries :: Python Modules
License-File: LICENSE
